fulladder/fulladder.vhdl
library IEEE;
use IEEE.STD_LOGIC_1164.ALL;

entity fulladder is
	Port(
		A : in STD_LOGIC;
		B : in STD_LOGIC;
		Cin : in STD_LOGIC;
		Sum : out STD_LOGIC;
		Carry : out STD_LOGIC
	);

end fulladder;

architecture logic_full_adder of fulladder is 
	begin
		Sum <= A xor B xor Cin;
		Carry <= (A and B) or (B and Cin) or (A and Cin);
end logic_full_adder;

fulladder/tb_full_adder.vhdl
library IEEE;
use IEEE.STD_LOGIC_1164.ALL;

entity tb_full_adder is
    -- No ports in a testbench
end tb_full_adder;

architecture Behavioral of tb_full_adder is
    -- Component declaration of the full adder
    component fulladder
        Port (
            A    : in  STD_LOGIC;
            B    : in  STD_LOGIC;
            Cin  : in  STD_LOGIC;
            Sum  : out STD_LOGIC;
            Carry : out STD_LOGIC
        );
    end component;

    -- Signal declarations
    signal A, B, Cin, Sum, Carry : STD_LOGIC;

begin
    -- Instantiate the full adder
    UUT: fulladder
        Port map (
            A => A,
            B => B,
            Cin => Cin,
            Sum => Sum,
            Carry => Carry
        );

    -- Stimulus process
    stim_proc: process
    begin
        -- Test case 1: A=0, B=0, Cin=0
        A <= '0'; B <= '0'; Cin <= '0';
        wait for 10 ns;

        -- Test case 2: A=0, B=0, Cin=1
        A <= '0'; B <= '0'; Cin <= '1';
        wait for 10 ns;

        -- Test case 3: A=0, B=1, Cin=0
        A <= '0'; B <= '1'; Cin <= '0';
        wait for 10 ns;

        -- Test case 4: A=0, B=1, Cin=1
        A <= '0'; B <= '1'; Cin <= '1';
        wait for 10 ns;

        -- Test case 5: A=1, B=0, Cin=0
        A <= '1'; B <= '0'; Cin <= '0';
        wait for 10 ns;

        -- Test case 6: A=1, B=0, Cin=1
        A <= '1'; B <= '0'; Cin <= '1';
        wait for 10 ns;

        -- Test case 7: A=1, B=1, Cin=0
        A <= '1'; B <= '1'; Cin <= '0';
        wait for 10 ns;

        -- Test case 8: A=1, B=1, Cin=1
        A <= '1'; B <= '1'; Cin <= '1';
        wait for 10 ns;

        -- End simulation
        wait;
    end process;

end Behavioral;

fulladder/fulladderwaveform.vcd
$date
  Tue Dec 24 05:50:06 2024
$end
$version
  GHDL v0
$end
$timescale
  1 fs
$end
$scope module standard $end
$upscope $end
$scope module std_logic_1164 $end
$upscope $end
$scope module tb_full_adder $end
$var reg 1 ! a $end
$var reg 1 " b $end
$var reg 1 # cin $end
$var reg 1 $ sum $end
$var reg 1 % carry $end
$scope module uut $end
$var reg 1 & a $end
$var reg 1 ' b $end
$var reg 1 ( cin $end
$var reg 1 ) sum $end
$var reg 1 * carry $end
$upscope $end
$upscope $end
$enddefinitions $end
#0
0!
0"
0#
0$
0%
0&
0'
0(
0)
0*
#10000000
1#
1$
1(
1)
#20000000
1"
0#
1'
0(
#30000000
1#
0$
1%
1(
0)
1*
#40000000
1!
0"
0#
1$
0%
1&
0'
0(
1)
0*
#50000000
1#
0$
1%
1(
0)
1*
#60000000
1"
0#
1'
0(
#70000000
1#
1$
1(
1)
